spiderplot/__init__.py
spiderplot/_demo.py
spiderplot/_spider.py
spiderplot-0.1.1.dist-info/LICENSE
spiderplot-0.1.1.dist-info/METADATA
spiderplot-0.1.1.dist-info/WHEEL
spiderplot-0.1.1.dist-info/top_level.txt
spiderplot-0.1.1.dist-info/RECORD
