Metadata-Version: 2.1
Name: spiderplot
Version: 0.1.1
Summary: Seaborn-style utility to plot spider charts
Home-page: https://github.com/hirsch-lab/spiderplot
Author: Norman Juchler
License: MIT
Keywords: spider chart,plotting
Platform: UNKNOWN
Classifier: Programming Language :: Python :: 3
Classifier: License :: OSI Approved :: MIT License
Classifier: Operating System :: OS Independent
Classifier: Topic :: Scientific/Engineering :: Mathematics
Classifier: Topic :: Scientific/Engineering :: Visualization
Classifier: Topic :: Utilities
Classifier: Intended Audience :: Developers
Classifier: Intended Audience :: Science/Research
Requires-Python: >=3.6
